{
  "EncounterName": "DENSE_VEGETATION_EVENT_ENCOUNTER",
  "Floor": 6,
  "Character": "IRONCLAD",
  "AscensionLevel": 0,
  "StartTime": "2026-07-06T14:45:12.1383644+08:00",
  "EndTime": "2026-07-06T14:45:28.8542246+08:00",
  "DurationSeconds": 16.7158602,
  "Victory": true,
  "EndHp": 53,
  "TotalTurns": 9,
  "TotalDamageDealt": 0,
  "TotalDamageTaken": 33,
  "TotalEnemiesKilled": 3,
  "SolverCrashes": 0,
  "Turns": [
    {
      "TurnNumber": 1,
      "Energy": 3,
      "Block": 0,
      "Hp": 80,
      "MaxHp": 80,
      "DrawPileCount": 8,
      "DiscardPileCount": 0,
      "Hand": [
        {
          "Id": "STRIKE_IRONCLAD",
          "Cost": 1
        },
        {
          "Id": "STRIKE_IRONCLAD",
          "Cost": 1
        },
        {
          "Id": "DEFEND_IRONCLAD",
          "Cost": 1
        },
        {
          "Id": "PREDATOR",
          "Cost": 2
        },
        {
          "Id": "STRIKE_IRONCLAD",
          "Cost": 1
        }
      ],
      "Enemies": [
        {
          "Index": 0,
          "Id": "WRIGGLER",
          "Hp": 21,
          "MaxHp": 21,
          "Block": 0,
          "IntentDamage": 6,
          "IntentType": "Attack",
          "VulnerableStacks": 0,
          "WeakStacks": 0,
          "StrengthStacks": 0,
          "Powers": []
        },
        {
          "Index": 1,
          "Id": "WRIGGLER",
          "Hp": 18,
          "MaxHp": 18,
          "Block": 0,
          "IntentDamage": 0,
          "IntentType": "Buff",
          "VulnerableStacks": 0,
          "WeakStacks": 0,
          "StrengthStacks": 0,
          "Powers": []
        },
        {
          "Index": 2,
          "Id": "WRIGGLER",
          "Hp": 20,
          "MaxHp": 20,
          "Block": 0,
          "IntentDamage": 6,
          "IntentType": "Attack",
          "VulnerableStacks": 0,
          "WeakStacks": 0,
          "StrengthStacks": 0,
          "Powers": []
        },
        {
          "Index": 3,
          "Id": "WRIGGLER",
          "Hp": 19,
          "MaxHp": 19,
          "Block": 0,
          "IntentDamage": 0,
          "IntentType": "Buff",
          "VulnerableStacks": 0,
          "WeakStacks": 0,
          "StrengthStacks": 0,
          "Powers": []
        }
      ],
      "PlayerPowers": {
        "Strength": 0,
        "Dexterity": 0,
        "Weak": 0,
        "Frail": 0,
        "Vulnerable": 0
      },
      "Orbs": {
        "OrbSlots": 0,
        "Lightning": 0,
        "Frost": 0,
        "Dark": 0,
        "Plasma": 0,
        "Focus": 0,
        "Stars": 0
      },
      "PotionIds": [
        "SKILL_POTION",
        "STRENGTH_POTION",
        "DEXTERITY_POTION"
      ],
      "PotionCount": 3,
      "SolverPlan": {
        "Actions": [
          "PLAY PREDATOR -\u003E WRIGGLER",
          "USE_POTION SKILL_POTION",
          "USE_POTION STRENGTH_POTION",
          "USE_POTION DEXTERITY_POTION",
          "PLAY STRIKE_IRONCLAD -\u003E WRIGGLER",
          "PLAY DEFEND_IRONCLAD -\u003E self",
          "END_TURN"
        ],
        "EstimatedDamage": 23,
        "EstimatedBlock": 9,
        "Score": "Dmg=23 Blk=9 In=12 Cards=7 Score=1256 States=5004 Char=IRONCLAD Src=reflection: dmg=15 blk=0",
        "StatesExplored": 5004
      },
      "ActionResults": [
        {
          "CardId": "PREDATOR",
          "Success": true,
          "Target": "WRIGGLER"
        }
      ],
      "Outcome": {
        "HpAfter": 80,
        "BlockAfter": 0,
        "DamageTaken": 0,
        "EnemiesKilled": 0,
        "EnergyRemaining": 0,
        "PlayableCardsNotPlayed": 0,
        "TotalPlayableInHand": 5,
        "Issues": []
      }
    },
    {
      "TurnNumber": 2,
      "Energy": 1,
      "Block": 0,
      "Hp": 80,
      "MaxHp": 80,
      "DrawPileCount": 8,
      "DiscardPileCount": 1,
      "Hand": [
        {
          "Id": "STRIKE_IRONCLAD",
          "Cost": 1
        },
        {
          "Id": "STRIKE_IRONCLAD",
          "Cost": 1
        },
        {
          "Id": "DEFEND_IRONCLAD",
          "Cost": 1
        },
        {
          "Id": "STRIKE_IRONCLAD",
          "Cost": 1
        },
        {
          "Id": "CASCADE",
          "Cost": -1
        }
      ],
      "Enemies": [
        {
          "Index": 0,
          "Id": "WRIGGLER",
          "Hp": 21,
          "MaxHp": 21,
          "Block": 0,
          "IntentDamage": 6,
          "IntentType": "Attack",
          "VulnerableStacks": 0,
          "WeakStacks": 0,
          "StrengthStacks": 0,
          "Powers": []
        },
        {
          "Index": 1,
          "Id": "WRIGGLER",
          "Hp": 3,
          "MaxHp": 18,
          "Block": 0,
          "IntentDamage": 0,
          "IntentType": "Buff",
          "VulnerableStacks": 0,
          "WeakStacks": 0,
          "StrengthStacks": 0,
          "Powers": []
        },
        {
          "Index": 2,
          "Id": "WRIGGLER",
          "Hp": 20,
          "MaxHp": 20,
          "Block": 0,
          "IntentDamage": 6,
          "IntentType": "Attack",
          "VulnerableStacks": 0,
          "WeakStacks": 0,
          "StrengthStacks": 0,
          "Powers": []
        },
        {
          "Index": 3,
          "Id": "WRIGGLER",
          "Hp": 19,
          "MaxHp": 19,
          "Block": 0,
          "IntentDamage": 0,
          "IntentType": "Buff",
          "VulnerableStacks": 0,
          "WeakStacks": 0,
          "StrengthStacks": 0,
          "Powers": []
        }
      ],
      "PlayerPowers": {
        "Strength": 0,
        "Dexterity": 0,
        "Weak": 0,
        "Frail": 0,
        "Vulnerable": 0
      },
      "Orbs": {
        "OrbSlots": 0,
        "Lightning": 0,
        "Frost": 0,
        "Dark": 0,
        "Plasma": 0,
        "Focus": 0,
        "Stars": 0
      },
      "PotionIds": [
        "STRENGTH_POTION",
        "DEXTERITY_POTION"
      ],
      "PotionCount": 2,
      "SolverPlan": {
        "Actions": [
          "USE_POTION STRENGTH_POTION",
          "USE_POTION DEXTERITY_POTION",
          "PLAY STRIKE_IRONCLAD -\u003E WRIGGLER",
          "PLAY CASCADE -\u003E self",
          "END_TURN"
        ],
        "EstimatedDamage": 8,
        "EstimatedBlock": 4,
        "Score": "Dmg=8 Blk=4 In=12 Cards=5 Score=504 States=405 Char=IRONCLAD Src=reflection: dmg=6 blk=0",
        "StatesExplored": 405
      },
      "ActionResults": [],
      "Outcome": {
        "HpAfter": 80,
        "BlockAfter": 0,
        "DamageTaken": 0,
        "EnemiesKilled": 0,
        "EnergyRemaining": 0,
        "PlayableCardsNotPlayed": 1,
        "TotalPlayableInHand": 5,
        "Issues": [
          "CARDS_UNPLAYED: 1 playable cards left at 0 energy"
        ]
      }
    },
    {
      "TurnNumber": 3,
      "Energy": 1,
      "Block": 0,
      "Hp": 80,
      "MaxHp": 80,
      "DrawPileCount": 8,
      "DiscardPileCount": 1,
      "Hand": [
        {
          "Id": "STRIKE_IRONCLAD",
          "Cost": 1
        },
        {
          "Id": "STRIKE_IRONCLAD",
          "Cost": 1
        },
        {
          "Id": "DEFEND_IRONCLAD",
          "Cost": 1
        },
        {
          "Id": "STRIKE_IRONCLAD",
          "Cost": 1
        },
        {
          "Id": "CASCADE",
          "Cost": -1
        }
      ],
      "Enemies": [
        {
          "Index": 0,
          "Id": "WRIGGLER",
          "Hp": 21,
          "MaxHp": 21,
          "Block": 0,
          "IntentDamage": 6,
          "IntentType": "Attack",
          "VulnerableStacks": 0,
          "WeakStacks": 0,
          "StrengthStacks": 0,
          "Powers": []
        },
        {
          "Index": 1,
          "Id": "WRIGGLER",
          "Hp": 3,
          "MaxHp": 18,
          "Block": 0,
          "IntentDamage": 0,
          "IntentType": "Buff",
          "VulnerableStacks": 0,
          "WeakStacks": 0,
          "StrengthStacks": 0,
          "Powers": []
        },
        {
          "Index": 2,
          "Id": "WRIGGLER",
          "Hp": 20,
          "MaxHp": 20,
          "Block": 0,
          "IntentDamage": 6,
          "IntentType": "Attack",
          "VulnerableStacks": 0,
          "WeakStacks": 0,
          "StrengthStacks": 0,
          "Powers": []
        },
        {
          "Index": 3,
          "Id": "WRIGGLER",
          "Hp": 19,
          "MaxHp": 19,
          "Block": 0,
          "IntentDamage": 0,
          "IntentType": "Buff",
          "VulnerableStacks": 0,
          "WeakStacks": 0,
          "StrengthStacks": 0,
          "Powers": []
        }
      ],
      "PlayerPowers": {
        "Strength": 2,
        "Dexterity": 0,
        "Weak": 0,
        "Frail": 0,
        "Vulnerable": 0
      },
      "Orbs": {
        "OrbSlots": 0,
        "Lightning": 0,
        "Frost": 0,
        "Dark": 0,
        "Plasma": 0,
        "Focus": 0,
        "Stars": 0
      },
      "PotionIds": [
        "DEXTERITY_POTION"
      ],
      "PotionCount": 1,
      "SolverPlan": {
        "Actions": [
          "USE_POTION DEXTERITY_POTION",
          "PLAY STRIKE_IRONCLAD -\u003E WRIGGLER",
          "PLAY CASCADE -\u003E self",
          "END_TURN"
        ],
        "EstimatedDamage": 10,
        "EstimatedBlock": 4,
        "Score": "Dmg=10 Blk=4 In=12 Cards=4 Score=468 States=95 Char=IRONCLAD Src=reflection: dmg=8 blk=0",
        "StatesExplored": 95
      },
      "ActionResults": [],
      "Outcome": {
        "HpAfter": 80,
        "BlockAfter": 0,
        "DamageTaken": 0,
        "EnemiesKilled": 0,
        "EnergyRemaining": 0,
        "PlayableCardsNotPlayed": 2,
        "TotalPlayableInHand": 5,
        "Issues": [
          "CARDS_UNPLAYED: 2 playable cards left at 0 energy"
        ]
      }
    },
    {
      "TurnNumber": 4,
      "Energy": 1,
      "Block": 0,
      "Hp": 80,
      "MaxHp": 80,
      "DrawPileCount": 8,
      "DiscardPileCount": 1,
      "Hand": [
        {
          "Id": "STRIKE_IRONCLAD",
          "Cost": 1
        },
        {
          "Id": "STRIKE_IRONCLAD",
          "Cost": 1
        },
        {
          "Id": "DEFEND_IRONCLAD",
          "Cost": 1
        },
        {
          "Id": "STRIKE_IRONCLAD",
          "Cost": 1
        },
        {
          "Id": "CASCADE",
          "Cost": -1
        }
      ],
      "Enemies": [
        {
          "Index": 0,
          "Id": "WRIGGLER",
          "Hp": 21,
          "MaxHp": 21,
          "Block": 0,
          "IntentDamage": 6,
          "IntentType": "Attack",
          "VulnerableStacks": 0,
          "WeakStacks": 0,
          "StrengthStacks": 0,
          "Powers": []
        },
        {
          "Index": 1,
          "Id": "WRIGGLER",
          "Hp": 3,
          "MaxHp": 18,
          "Block": 0,
          "IntentDamage": 0,
          "IntentType": "Buff",
          "VulnerableStacks": 0,
          "WeakStacks": 0,
          "StrengthStacks": 0,
          "Powers": []
        },
        {
          "Index": 2,
          "Id": "WRIGGLER",
          "Hp": 20,
          "MaxHp": 20,
          "Block": 0,
          "IntentDamage": 6,
          "IntentType": "Attack",
          "VulnerableStacks": 0,
          "WeakStacks": 0,
          "StrengthStacks": 0,
          "Powers": []
        },
        {
          "Index": 3,
          "Id": "WRIGGLER",
          "Hp": 19,
          "MaxHp": 19,
          "Block": 0,
          "IntentDamage": 0,
          "IntentType": "Buff",
          "VulnerableStacks": 0,
          "WeakStacks": 0,
          "StrengthStacks": 0,
          "Powers": []
        }
      ],
      "PlayerPowers": {
        "Strength": 2,
        "Dexterity": 2,
        "Weak": 0,
        "Frail": 0,
        "Vulnerable": 0
      },
      "Orbs": {
        "OrbSlots": 0,
        "Lightning": 0,
        "Frost": 0,
        "Dark": 0,
        "Plasma": 0,
        "Focus": 0,
        "Stars": 0
      },
      "PotionIds": [],
      "PotionCount": 0,
      "SolverPlan": {
        "Actions": [
          "PLAY STRIKE_IRONCLAD -\u003E WRIGGLER",
          "PLAY CASCADE -\u003E self",
          "END_TURN"
        ],
        "EstimatedDamage": 10,
        "EstimatedBlock": 4,
        "Score": "Dmg=10 Blk=4 In=12 Cards=3 Score=468 States=27 Char=IRONCLAD Src=reflection: dmg=8 blk=0",
        "StatesExplored": 27
      },
      "ActionResults": [
        {
          "CardId": "STRIKE_IRONCLAD",
          "Success": true,
          "Target": "WRIGGLER"
        },
        {
          "CardId": "CASCADE",
          "Success": true
        }
      ],
      "Outcome": {
        "HpAfter": 68,
        "BlockAfter": 0,
        "DamageTaken": 12,
        "EnemiesKilled": 1,
        "EnergyRemaining": 1,
        "PlayableCardsNotPlayed": 3,
        "TotalPlayableInHand": 5,
        "Issues": [
          "ENERGY_WASTED: 1 energy left, 3/5 playable cards not used"
        ]
      }
    },
    {
      "TurnNumber": 5,
      "Energy": 3,
      "Block": 0,
      "Hp": 68,
      "MaxHp": 80,
      "DrawPileCount": 3,
      "DiscardPileCount": 7,
      "Hand": [
        {
          "Id": "DEFEND_IRONCLAD",
          "Cost": 1
        },
        {
          "Id": "SETUP_STRIKE",
          "Cost": 1
        },
        {
          "Id": "DEFEND_IRONCLAD",
          "Cost": 1
        },
        {
          "Id": "BACKFLIP",
          "Cost": 1
        },
        {
          "Id": "STRIKE_IRONCLAD",
          "Cost": 1
        }
      ],
      "Enemies": [
        {
          "Index": 0,
          "Id": "WRIGGLER",
          "Hp": 21,
          "MaxHp": 21,
          "Block": 0,
          "IntentDamage": 0,
          "IntentType": "Buff",
          "VulnerableStacks": 0,
          "WeakStacks": 0,
          "StrengthStacks": 0,
          "Powers": []
        },
        {
          "Index": 1,
          "Id": "WRIGGLER",
          "Hp": 20,
          "MaxHp": 20,
          "Block": 0,
          "IntentDamage": 0,
          "IntentType": "Buff",
          "VulnerableStacks": 0,
          "WeakStacks": 0,
          "StrengthStacks": 0,
          "Powers": []
        },
        {
          "Index": 2,
          "Id": "WRIGGLER",
          "Hp": 19,
          "MaxHp": 19,
          "Block": 0,
          "IntentDamage": 8,
          "IntentType": "Attack",
          "VulnerableStacks": 0,
          "WeakStacks": 0,
          "StrengthStacks": 2,
          "Powers": [
            {
              "Name": "StrengthPower",
              "Amount": 2
            }
          ]
        }
      ],
      "PlayerPowers": {
        "Strength": 2,
        "Dexterity": 2,
        "Weak": 0,
        "Frail": 0,
        "Vulnerable": 0
      },
      "Orbs": {
        "OrbSlots": 0,
        "Lightning": 0,
        "Frost": 0,
        "Dark": 0,
        "Plasma": 0,
        "Focus": 0,
        "Stars": 0
      },
      "PotionIds": [],
      "PotionCount": 0,
      "SolverPlan": {
        "Actions": [
          "PLAY SETUP_STRIKE -\u003E WRIGGLER",
          "PLAY STRIKE_IRONCLAD -\u003E WRIGGLER",
          "PLAY BACKFLIP -\u003E self",
          "PLAY BATTLE_TRANCE -\u003E self",
          "END_TURN"
        ],
        "EstimatedDamage": 21,
        "EstimatedBlock": 15,
        "Score": "Dmg=21 Blk=15 In=8 Cards=5 Score=1509 States=1084 Char=IRONCLAD Src=reflection: dmg=9 blk=0",
        "StatesExplored": 1084
      },
      "ActionResults": [
        {
          "CardId": "SETUP_STRIKE",
          "Success": true,
          "Target": "WRIGGLER"
        },
        {
          "CardId": "STRIKE_IRONCLAD",
          "Success": true,
          "Target": "WRIGGLER"
        },
        {
          "CardId": "BACKFLIP",
          "Success": true
        },
        {
          "CardId": "BATTLE_TRANCE",
          "Success": true
        }
      ],
      "Outcome": {
        "HpAfter": 64,
        "BlockAfter": 0,
        "DamageTaken": 4,
        "EnemiesKilled": 0,
        "EnergyRemaining": 0,
        "PlayableCardsNotPlayed": 1,
        "TotalPlayableInHand": 5,
        "Issues": [
          "CARDS_UNPLAYED: 1 playable cards left at 0 energy"
        ]
      }
    },
    {
      "TurnNumber": 6,
      "Energy": 3,
      "Block": 0,
      "Hp": 64,
      "MaxHp": 80,
      "DrawPileCount": 0,
      "DiscardPileCount": 12,
      "Hand": [
        {
          "Id": "CASCADE",
          "Cost": -1
        },
        {
          "Id": "DEFEND_IRONCLAD",
          "Cost": 1
        },
        {
          "Id": "PREDATOR",
          "Cost": 2
        },
        {
          "Id": "STRIKE_IRONCLAD",
          "Cost": 1
        },
        {
          "Id": "STRIKE_IRONCLAD",
          "Cost": 1
        }
      ],
      "Enemies": [
        {
          "Index": 0,
          "Id": "WRIGGLER",
          "Hp": 2,
          "MaxHp": 21,
          "Block": 0,
          "IntentDamage": 8,
          "IntentType": "Attack",
          "VulnerableStacks": 0,
          "WeakStacks": 0,
          "StrengthStacks": 2,
          "Powers": [
            {
              "Name": "StrengthPower",
              "Amount": 2
            }
          ]
        },
        {
          "Index": 1,
          "Id": "WRIGGLER",
          "Hp": 20,
          "MaxHp": 20,
          "Block": 0,
          "IntentDamage": 8,
          "IntentType": "Attack",
          "VulnerableStacks": 0,
          "WeakStacks": 0,
          "StrengthStacks": 2,
          "Powers": [
            {
              "Name": "StrengthPower",
              "Amount": 2
            }
          ]
        },
        {
          "Index": 2,
          "Id": "WRIGGLER",
          "Hp": 19,
          "MaxHp": 19,
          "Block": 0,
          "IntentDamage": 0,
          "IntentType": "Buff",
          "VulnerableStacks": 0,
          "WeakStacks": 0,
          "StrengthStacks": 2,
          "Powers": [
            {
              "Name": "StrengthPower",
              "Amount": 2
            }
          ]
        }
      ],
      "PlayerPowers": {
        "Strength": 2,
        "Dexterity": 2,
        "Weak": 0,
        "Frail": 0,
        "Vulnerable": 0
      },
      "Orbs": {
        "OrbSlots": 0,
        "Lightning": 0,
        "Frost": 0,
        "Dark": 0,
        "Plasma": 0,
        "Focus": 0,
        "Stars": 0
      },
      "PotionIds": [],
      "PotionCount": 0,
      "SolverPlan": {
        "Actions": [
          "PLAY PREDATOR -\u003E WRIGGLER",
          "PLAY STRIKE_IRONCLAD -\u003E WRIGGLER",
          "PLAY CASCADE -\u003E self",
          "END_TURN"
        ],
        "EstimatedDamage": 29,
        "EstimatedBlock": 6,
        "Score": "Dmg=29 Blk=6 In=16 Cards=4 Score=2234 States=327 Char=IRONCLAD Src=reflection: dmg=17 blk=0",
        "StatesExplored": 327
      },
      "ActionResults": [
        {
          "CardId": "PREDATOR",
          "Success": true,
          "Target": "WRIGGLER"
        },
        {
          "CardId": "STRIKE_IRONCLAD",
          "Success": true,
          "Target": "WRIGGLER"
        },
        {
          "CardId": "CASCADE",
          "Success": true
        }
      ],
      "Outcome": {
        "HpAfter": 56,
        "BlockAfter": 0,
        "DamageTaken": 8,
        "EnemiesKilled": 1,
        "EnergyRemaining": 0,
        "PlayableCardsNotPlayed": 2,
        "TotalPlayableInHand": 5,
        "Issues": [
          "CARDS_UNPLAYED: 2 playable cards left at 0 energy"
        ]
      }
    },
    {
      "TurnNumber": 7,
      "Energy": 3,
      "Block": 0,
      "Hp": 56,
      "MaxHp": 80,
      "DrawPileCount": 13,
      "DiscardPileCount": 0,
      "Hand": [
        {
          "Id": "DEFEND_IRONCLAD",
          "Cost": 1
        },
        {
          "Id": "STRIKE_IRONCLAD",
          "Cost": 1
        },
        {
          "Id": "CASCADE",
          "Cost": -1
        },
        {
          "Id": "DEFEND_IRONCLAD",
          "Cost": 1
        },
        {
          "Id": "INFECTION",
          "Cost": -1
        }
      ],
      "Enemies": [
        {
          "Index": 0,
          "Id": "WRIGGLER",
          "Hp": 20,
          "MaxHp": 20,
          "Block": 0,
          "IntentDamage": 0,
          "IntentType": "Buff",
          "VulnerableStacks": 0,
          "WeakStacks": 0,
          "StrengthStacks": 2,
          "Powers": [
            {
              "Name": "StrengthPower",
              "Amount": 2
            }
          ]
        },
        {
          "Index": 1,
          "Id": "WRIGGLER",
          "Hp": 2,
          "MaxHp": 19,
          "Block": 0,
          "IntentDamage": 10,
          "IntentType": "Attack",
          "VulnerableStacks": 0,
          "WeakStacks": 0,
          "StrengthStacks": 4,
          "Powers": [
            {
              "Name": "StrengthPower",
              "Amount": 4
            }
          ]
        }
      ],
      "PlayerPowers": {
        "Strength": 2,
        "Dexterity": 2,
        "Weak": 0,
        "Frail": 0,
        "Vulnerable": 0
      },
      "Orbs": {
        "OrbSlots": 0,
        "Lightning": 0,
        "Frost": 0,
        "Dark": 0,
        "Plasma": 0,
        "Focus": 0,
        "Stars": 0
      },
      "PotionIds": [],
      "PotionCount": 0,
      "SolverPlan": {
        "Actions": [
          "PLAY STRIKE_IRONCLAD -\u003E WRIGGLER",
          "PLAY DEFEND_IRONCLAD -\u003E self",
          "PLAY DEFEND_IRONCLAD -\u003E self",
          "PLAY CASCADE -\u003E self",
          "END_TURN"
        ],
        "EstimatedDamage": 10,
        "EstimatedBlock": 22,
        "Score": "Dmg=10 Blk=22 In=10 Cards=5 Score=1276 States=87 Char=IRONCLAD Src=reflection: dmg=8 blk=0",
        "StatesExplored": 87
      },
      "ActionResults": [
        {
          "CardId": "STRIKE_IRONCLAD",
          "Success": true,
          "Target": "WRIGGLER"
        },
        {
          "CardId": "DEFEND_IRONCLAD",
          "Success": true
        },
        {
          "CardId": "DEFEND_IRONCLAD",
          "Success": true
        },
        {
          "CardId": "CASCADE",
          "Success": true
        }
      ],
      "Outcome": {
        "HpAfter": 56,
        "BlockAfter": 0,
        "DamageTaken": 0,
        "EnemiesKilled": 1,
        "EnergyRemaining": 0,
        "PlayableCardsNotPlayed": 0,
        "TotalPlayableInHand": 4,
        "Issues": []
      }
    },
    {
      "TurnNumber": 8,
      "Energy": 3,
      "Block": 0,
      "Hp": 56,
      "MaxHp": 80,
      "DrawPileCount": 6,
      "DiscardPileCount": 8,
      "Hand": [
        {
          "Id": "BACKFLIP",
          "Cost": 1
        },
        {
          "Id": "BATTLE_TRANCE",
          "Cost": 0
        },
        {
          "Id": "DEFEND_IRONCLAD",
          "Cost": 1
        },
        {
          "Id": "STRIKE_IRONCLAD",
          "Cost": 1
        },
        {
          "Id": "INFECTION",
          "Cost": -1
        }
      ],
      "Enemies": [
        {
          "Index": 0,
          "Id": "WRIGGLER",
          "Hp": 20,
          "MaxHp": 20,
          "Block": 0,
          "IntentDamage": 10,
          "IntentType": "Attack",
          "VulnerableStacks": 0,
          "WeakStacks": 0,
          "StrengthStacks": 4,
          "Powers": [
            {
              "Name": "StrengthPower",
              "Amount": 4
            }
          ]
        }
      ],
      "PlayerPowers": {
        "Strength": 2,
        "Dexterity": 2,
        "Weak": 0,
        "Frail": 0,
        "Vulnerable": 0
      },
      "Orbs": {
        "OrbSlots": 0,
        "Lightning": 0,
        "Frost": 0,
        "Dark": 0,
        "Plasma": 0,
        "Focus": 0,
        "Stars": 0
      },
      "PotionIds": [],
      "PotionCount": 0,
      "SolverPlan": {
        "Actions": [
          "PLAY BATTLE_TRANCE -\u003E self",
          "PLAY STRIKE_IRONCLAD -\u003E WRIGGLER",
          "PLAY BACKFLIP -\u003E self",
          "PLAY SETUP_STRIKE -\u003E WRIGGLER",
          "PLAY INFECTION -\u003E self",
          "END_TURN"
        ],
        "EstimatedDamage": 19,
        "EstimatedBlock": 17,
        "Score": "Dmg=19 Blk=17 In=10 Cards=6 Score=434 States=874 Char=IRONCLAD Src=fallback: dmg=0 blk=0",
        "StatesExplored": 874
      },
      "ActionResults": [
        {
          "CardId": "BATTLE_TRANCE",
          "Success": true
        },
        {
          "CardId": "STRIKE_IRONCLAD",
          "Success": true,
          "Target": "WRIGGLER"
        },
        {
          "CardId": "BACKFLIP",
          "Success": true
        },
        {
          "CardId": "SETUP_STRIKE",
          "Success": true,
          "Target": "WRIGGLER"
        },
        {
          "CardId": "INFECTION",
          "Success": false,
          "FailReason": "not playable: HasUnplayableKeyword"
        }
      ],
      "Outcome": {
        "HpAfter": 47,
        "BlockAfter": 0,
        "DamageTaken": 9,
        "EnemiesKilled": 0,
        "EnergyRemaining": 1,
        "PlayableCardsNotPlayed": 0,
        "TotalPlayableInHand": 4,
        "Issues": []
      }
    },
    {
      "TurnNumber": 9,
      "Energy": 3,
      "Block": 0,
      "Hp": 47,
      "MaxHp": 80,
      "DrawPileCount": 5,
      "DiscardPileCount": 11,
      "Hand": [
        {
          "Id": "STRIKE_IRONCLAD",
          "Cost": 1
        },
        {
          "Id": "PREDATOR",
          "Cost": 2
        },
        {
          "Id": "INFECTION",
          "Cost": -1
        }
      ],
      "Enemies": [
        {
          "Index": 0,
          "Id": "WRIGGLER",
          "Hp": 3,
          "MaxHp": 20,
          "Block": 0,
          "IntentDamage": 0,
          "IntentType": "Buff",
          "VulnerableStacks": 0,
          "WeakStacks": 0,
          "StrengthStacks": 4,
          "Powers": [
            {
              "Name": "StrengthPower",
              "Amount": 4
            }
          ]
        }
      ],
      "PlayerPowers": {
        "Strength": 2,
        "Dexterity": 2,
        "Weak": 0,
        "Frail": 0,
        "Vulnerable": 0
      },
      "Orbs": {
        "OrbSlots": 0,
        "Lightning": 0,
        "Frost": 0,
        "Dark": 0,
        "Plasma": 0,
        "Focus": 0,
        "Stars": 0
      },
      "PotionIds": [],
      "PotionCount": 0,
      "SolverPlan": {
        "Actions": [
          "PLAY PREDATOR -\u003E WRIGGLER",
          "END_TURN"
        ],
        "EstimatedDamage": 19,
        "EstimatedBlock": 2,
        "Score": "Dmg=19 Blk=2 In=0 Cards=2 Score=1334 States=2 Char=IRONCLAD Src=reflection: dmg=17 blk=0",
        "StatesExplored": 2
      },
      "ActionResults": [
        {
          "CardId": "PREDATOR",
          "Success": true,
          "Target": "WRIGGLER"
        }
      ],
      "Outcome": {
        "HpAfter": 53,
        "BlockAfter": 0,
        "DamageTaken": 0,
        "EnemiesKilled": 0,
        "EnergyRemaining": 0,
        "PlayableCardsNotPlayed": 0,
        "TotalPlayableInHand": 0,
        "Issues": []
      }
    }
  ]
}