{
  "EncounterName": "INKLETS_NORMAL",
  "Floor": 13,
  "Character": "IRONCLAD",
  "AscensionLevel": 0,
  "StartTime": "2026-07-06T14:10:17.3207953+08:00",
  "EndTime": "2026-07-06T14:10:23.0392957+08:00",
  "DurationSeconds": 5.7185004,
  "Victory": true,
  "EndHp": 45,
  "TotalTurns": 5,
  "TotalDamageDealt": 0,
  "TotalDamageTaken": 29,
  "TotalEnemiesKilled": 2,
  "SolverCrashes": 0,
  "Turns": [
    {
      "TurnNumber": 1,
      "Energy": 3,
      "Block": 0,
      "Hp": 68,
      "MaxHp": 80,
      "DrawPileCount": 10,
      "DiscardPileCount": 0,
      "Hand": [
        {
          "Id": "DEFEND_IRONCLAD",
          "Cost": 1
        },
        {
          "Id": "CINDER",
          "Cost": 2
        },
        {
          "Id": "ASHEN_STRIKE",
          "Cost": 1
        },
        {
          "Id": "DEFEND_IRONCLAD",
          "Cost": 1
        },
        {
          "Id": "STRIKE_IRONCLAD",
          "Cost": 1
        }
      ],
      "Enemies": [
        {
          "Index": 0,
          "Id": "INKLET",
          "Hp": 17,
          "MaxHp": 17,
          "Block": 0,
          "IntentDamage": 3,
          "IntentType": "Attack",
          "VulnerableStacks": 0,
          "WeakStacks": 0,
          "StrengthStacks": 0,
          "Powers": [
            {
              "Name": "SlipperyPower",
              "Amount": 1
            }
          ]
        },
        {
          "Index": 1,
          "Id": "INKLET",
          "Hp": 12,
          "MaxHp": 12,
          "Block": 0,
          "IntentDamage": 6,
          "IntentType": "Attack",
          "VulnerableStacks": 0,
          "WeakStacks": 0,
          "StrengthStacks": 0,
          "Powers": [
            {
              "Name": "SlipperyPower",
              "Amount": 1
            }
          ]
        },
        {
          "Index": 2,
          "Id": "INKLET",
          "Hp": 14,
          "MaxHp": 14,
          "Block": 0,
          "IntentDamage": 3,
          "IntentType": "Attack",
          "VulnerableStacks": 0,
          "WeakStacks": 0,
          "StrengthStacks": 0,
          "Powers": [
            {
              "Name": "SlipperyPower",
              "Amount": 1
            }
          ]
        }
      ],
      "PlayerPowers": {
        "Strength": 0,
        "Dexterity": 0,
        "Weak": 0,
        "Frail": 0,
        "Vulnerable": 0
      },
      "Orbs": {
        "OrbSlots": 0,
        "Lightning": 0,
        "Frost": 0,
        "Dark": 0,
        "Plasma": 0,
        "Focus": 0,
        "Stars": 0
      },
      "PotionIds": [
        "COLORLESS_POTION"
      ],
      "PotionCount": 1,
      "SolverPlan": {
        "Actions": [
          "PLAY CINDER -\u003E INKLET",
          "PLAY ASHEN_STRIKE -\u003E INKLET",
          "USE_POTION COLORLESS_POTION",
          "PLAY STRIKE_IRONCLAD -\u003E INKLET",
          "END_TURN"
        ],
        "EstimatedDamage": 36,
        "EstimatedBlock": 0,
        "Score": "Dmg=36 Blk=0 In=12 Cards=5 Score=2277 States=2892 Char=IRONCLAD Src=reflection: dmg=24 blk=0",
        "StatesExplored": 2892
      },
      "ActionResults": [
        {
          "CardId": "CINDER",
          "Success": true,
          "Target": "INKLET"
        },
        {
          "CardId": "ASHEN_STRIKE",
          "Success": true,
          "Target": "INKLET"
        }
      ],
      "Outcome": {
        "HpAfter": 68,
        "BlockAfter": 0,
        "DamageTaken": 0,
        "EnemiesKilled": 0,
        "EnergyRemaining": 0,
        "PlayableCardsNotPlayed": 1,
        "TotalPlayableInHand": 5,
        "Issues": [
          "CARDS_UNPLAYED: 1 playable cards left at 0 energy"
        ]
      }
    },
    {
      "TurnNumber": 2,
      "Energy": 0,
      "Block": 0,
      "Hp": 68,
      "MaxHp": 80,
      "DrawPileCount": 10,
      "DiscardPileCount": 2,
      "Hand": [
        {
          "Id": "DEFEND_IRONCLAD",
          "Cost": 1
        },
        {
          "Id": "STRIKE_IRONCLAD",
          "Cost": 1
        },
        {
          "Id": "VOLLEY",
          "Cost": -1
        }
      ],
      "Enemies": [
        {
          "Index": 0,
          "Id": "INKLET",
          "Hp": 16,
          "MaxHp": 17,
          "Block": 0,
          "IntentDamage": 3,
          "IntentType": "Attack",
          "VulnerableStacks": 0,
          "WeakStacks": 0,
          "StrengthStacks": 0,
          "Powers": []
        },
        {
          "Index": 1,
          "Id": "INKLET",
          "Hp": 11,
          "MaxHp": 12,
          "Block": 0,
          "IntentDamage": 6,
          "IntentType": "Attack",
          "VulnerableStacks": 0,
          "WeakStacks": 0,
          "StrengthStacks": 0,
          "Powers": []
        },
        {
          "Index": 2,
          "Id": "INKLET",
          "Hp": 14,
          "MaxHp": 14,
          "Block": 0,
          "IntentDamage": 3,
          "IntentType": "Attack",
          "VulnerableStacks": 0,
          "WeakStacks": 0,
          "StrengthStacks": 0,
          "Powers": [
            {
              "Name": "SlipperyPower",
              "Amount": 1
            }
          ]
        }
      ],
      "PlayerPowers": {
        "Strength": 0,
        "Dexterity": 0,
        "Weak": 0,
        "Frail": 0,
        "Vulnerable": 0
      },
      "Orbs": {
        "OrbSlots": 0,
        "Lightning": 0,
        "Frost": 0,
        "Dark": 0,
        "Plasma": 0,
        "Focus": 0,
        "Stars": 0
      },
      "PotionIds": [],
      "PotionCount": 0,
      "SolverPlan": {
        "Actions": [
          "END_TURN"
        ],
        "EstimatedDamage": 0,
        "EstimatedBlock": 0,
        "Score": "Dmg=0 Blk=0 In=12 Cards=1 Score=-1200 States=1 Char=IRONCLAD Src=reflection: dmg=10 blk=0",
        "StatesExplored": 1
      },
      "ActionResults": [],
      "Outcome": {
        "HpAfter": 56,
        "BlockAfter": 0,
        "DamageTaken": 12,
        "EnemiesKilled": 0,
        "EnergyRemaining": 3,
        "PlayableCardsNotPlayed": 1,
        "TotalPlayableInHand": 1,
        "Issues": [
          "ENERGY_WASTED: 3 energy left, 1/1 playable cards not used"
        ]
      }
    },
    {
      "TurnNumber": 3,
      "Energy": 3,
      "Block": 0,
      "Hp": 56,
      "MaxHp": 80,
      "DrawPileCount": 5,
      "DiscardPileCount": 5,
      "Hand": [
        {
          "Id": "PILLAGE",
          "Cost": 1
        },
        {
          "Id": "STRIKE_IRONCLAD",
          "Cost": 1
        },
        {
          "Id": "BREAKTHROUGH",
          "Cost": 1
        },
        {
          "Id": "STRIKE_IRONCLAD",
          "Cost": 1
        },
        {
          "Id": "DEFEND_IRONCLAD",
          "Cost": 1
        }
      ],
      "Enemies": [
        {
          "Index": 0,
          "Id": "INKLET",
          "Hp": 16,
          "MaxHp": 17,
          "Block": 0,
          "IntentDamage": 10,
          "IntentType": "Attack",
          "VulnerableStacks": 0,
          "WeakStacks": 0,
          "StrengthStacks": 0,
          "Powers": []
        },
        {
          "Index": 1,
          "Id": "INKLET",
          "Hp": 11,
          "MaxHp": 12,
          "Block": 0,
          "IntentDamage": 3,
          "IntentType": "Attack",
          "VulnerableStacks": 0,
          "WeakStacks": 0,
          "StrengthStacks": 0,
          "Powers": []
        },
        {
          "Index": 2,
          "Id": "INKLET",
          "Hp": 14,
          "MaxHp": 14,
          "Block": 0,
          "IntentDamage": 6,
          "IntentType": "Attack",
          "VulnerableStacks": 0,
          "WeakStacks": 0,
          "StrengthStacks": 0,
          "Powers": [
            {
              "Name": "SlipperyPower",
              "Amount": 1
            }
          ]
        }
      ],
      "PlayerPowers": {
        "Strength": 0,
        "Dexterity": 0,
        "Weak": 0,
        "Frail": 0,
        "Vulnerable": 0
      },
      "Orbs": {
        "OrbSlots": 0,
        "Lightning": 0,
        "Frost": 0,
        "Dark": 0,
        "Plasma": 0,
        "Focus": 0,
        "Stars": 0
      },
      "PotionIds": [],
      "PotionCount": 0,
      "SolverPlan": {
        "Actions": [
          "PLAY BREAKTHROUGH -\u003E INKLET",
          "PLAY PILLAGE -\u003E INKLET",
          "PLAY STRIKE_IRONCLAD -\u003E INKLET",
          "END_TURN"
        ],
        "EstimatedDamage": 39,
        "EstimatedBlock": 0,
        "Score": "Dmg=39 Blk=0 In=19 Cards=4 Score=1598 States=613 Char=IRONCLAD Src=reflection: dmg=6 blk=0",
        "StatesExplored": 613
      },
      "ActionResults": [
        {
          "CardId": "BREAKTHROUGH",
          "Success": true,
          "Target": "INKLET"
        },
        {
          "CardId": "PILLAGE",
          "Success": true,
          "Target": "INKLET"
        },
        {
          "CardId": "STRIKE_IRONCLAD",
          "Success": true,
          "Target": "INKLET"
        }
      ],
      "Outcome": {
        "HpAfter": 39,
        "BlockAfter": 0,
        "DamageTaken": 17,
        "EnemiesKilled": 1,
        "EnergyRemaining": 0,
        "PlayableCardsNotPlayed": 2,
        "TotalPlayableInHand": 5,
        "Issues": [
          "CARDS_UNPLAYED: 2 playable cards left at 0 energy"
        ]
      }
    },
    {
      "TurnNumber": 4,
      "Energy": 3,
      "Block": 0,
      "Hp": 39,
      "MaxHp": 80,
      "DrawPileCount": 5,
      "DiscardPileCount": 8,
      "Hand": [
        {
          "Id": "MOLTEN_FIST",
          "Cost": 1
        },
        {
          "Id": "GUILTY",
          "Cost": -1
        }
      ],
      "Enemies": [
        {
          "Index": 0,
          "Id": "INKLET",
          "Hp": 7,
          "MaxHp": 17,
          "Block": 0,
          "IntentDamage": 3,
          "IntentType": "Attack",
          "VulnerableStacks": 0,
          "WeakStacks": 0,
          "StrengthStacks": 0,
          "Powers": []
        },
        {
          "Index": 1,
          "Id": "INKLET",
          "Hp": 7,
          "MaxHp": 14,
          "Block": 0,
          "IntentDamage": 3,
          "IntentType": "Attack",
          "VulnerableStacks": 0,
          "WeakStacks": 0,
          "StrengthStacks": 0,
          "Powers": []
        }
      ],
      "PlayerPowers": {
        "Strength": 0,
        "Dexterity": 0,
        "Weak": 0,
        "Frail": 0,
        "Vulnerable": 0
      },
      "Orbs": {
        "OrbSlots": 0,
        "Lightning": 0,
        "Frost": 0,
        "Dark": 0,
        "Plasma": 0,
        "Focus": 0,
        "Stars": 0
      },
      "PotionIds": [],
      "PotionCount": 0,
      "SolverPlan": {
        "Actions": [
          "PLAY MOLTEN_FIST -\u003E INKLET",
          "END_TURN"
        ],
        "EstimatedDamage": 10,
        "EstimatedBlock": 0,
        "Score": "Dmg=10 Blk=0 In=6 Cards=2 Score=486 States=2 Char=IRONCLAD Src=reflection: dmg=10 blk=0",
        "StatesExplored": 2
      },
      "ActionResults": [
        {
          "CardId": "MOLTEN_FIST",
          "Success": true,
          "Target": "INKLET"
        }
      ],
      "Outcome": {
        "HpAfter": 39,
        "BlockAfter": 0,
        "DamageTaken": 0,
        "EnemiesKilled": 1,
        "EnergyRemaining": 1,
        "PlayableCardsNotPlayed": 0,
        "TotalPlayableInHand": 1,
        "Issues": []
      }
    },
    {
      "TurnNumber": 5,
      "Energy": 2,
      "Block": 0,
      "Hp": 39,
      "MaxHp": 80,
      "DrawPileCount": 10,
      "DiscardPileCount": 0,
      "Hand": [
        {
          "Id": "GUILTY",
          "Cost": -1
        },
        {
          "Id": "STRIKE_IRONCLAD",
          "Cost": 1
        },
        {
          "Id": "DEFEND_IRONCLAD",
          "Cost": 1
        },
        {
          "Id": "CINDER",
          "Cost": 2
        }
      ],
      "Enemies": [
        {
          "Index": 0,
          "Id": "INKLET",
          "Hp": 7,
          "MaxHp": 14,
          "Block": 0,
          "IntentDamage": 3,
          "IntentType": "Attack",
          "VulnerableStacks": 0,
          "WeakStacks": 0,
          "StrengthStacks": 0,
          "Powers": []
        }
      ],
      "PlayerPowers": {
        "Strength": 0,
        "Dexterity": 0,
        "Weak": 0,
        "Frail": 0,
        "Vulnerable": 0
      },
      "Orbs": {
        "OrbSlots": 0,
        "Lightning": 0,
        "Frost": 0,
        "Dark": 0,
        "Plasma": 0,
        "Focus": 0,
        "Stars": 0
      },
      "PotionIds": [],
      "PotionCount": 0,
      "SolverPlan": {
        "Actions": [
          "PLAY CINDER -\u003E INKLET",
          "END_TURN"
        ],
        "EstimatedDamage": 24,
        "EstimatedBlock": 0,
        "Score": "Dmg=24 Blk=0 In=3 Cards=2 Score=1233 States=5 Char=IRONCLAD Src=reflection: dmg=24 blk=0",
        "StatesExplored": 5
      },
      "ActionResults": [
        {
          "CardId": "CINDER",
          "Success": true,
          "Target": "INKLET"
        }
      ],
      "Outcome": {
        "HpAfter": 45,
        "BlockAfter": 0,
        "DamageTaken": 0,
        "EnemiesKilled": 0,
        "EnergyRemaining": 0,
        "PlayableCardsNotPlayed": 0,
        "TotalPlayableInHand": 0,
        "Issues": []
      }
    }
  ]
}