{
  "EncounterName": "PHANTASMAL_GARDENERS_ELITE",
  "Floor": 15,
  "Character": "IRONCLAD",
  "AscensionLevel": 0,
  "StartTime": "2026-07-06T16:49:03.9369414+08:00",
  "EndTime": "2026-07-06T16:49:12.1783543+08:00",
  "DurationSeconds": 8.2414129,
  "Victory": true,
  "EndHp": 16,
  "TotalTurns": 6,
  "TotalDamageDealt": 0,
  "TotalDamageTaken": 25,
  "TotalEnemiesKilled": 3,
  "SolverCrashes": 0,
  "Turns": [
    {
      "TurnNumber": 1,
      "Energy": 3,
      "Block": 0,
      "Hp": 35,
      "MaxHp": 80,
      "DrawPileCount": 15,
      "DiscardPileCount": 0,
      "Hand": [
        {
          "Id": "PERFECTED_STRIKE",
          "Cost": 2
        },
        {
          "Id": "DEFEND_IRONCLAD",
          "Cost": 1
        },
        {
          "Id": "STRIKE_IRONCLAD",
          "Cost": 1
        },
        {
          "Id": "STRIKE_IRONCLAD",
          "Cost": 1
        },
        {
          "Id": "UNRELENTING",
          "Cost": 2
        }
      ],
      "Enemies": [
        {
          "Index": 0,
          "Id": "PHANTASMAL_GARDENER",
          "Hp": 26,
          "MaxHp": 26,
          "Block": 0,
          "IntentDamage": 3,
          "IntentType": "Attack",
          "VulnerableStacks": 0,
          "WeakStacks": 0,
          "StrengthStacks": 0,
          "Powers": [
            {
              "Name": "SkittishPower",
              "Amount": 6
            }
          ]
        },
        {
          "Index": 1,
          "Id": "PHANTASMAL_GARDENER",
          "Hp": 29,
          "MaxHp": 29,
          "Block": 0,
          "IntentDamage": 5,
          "IntentType": "Attack",
          "VulnerableStacks": 0,
          "WeakStacks": 0,
          "StrengthStacks": 0,
          "Powers": [
            {
              "Name": "SkittishPower",
              "Amount": 6
            }
          ]
        },
        {
          "Index": 2,
          "Id": "PHANTASMAL_GARDENER",
          "Hp": 27,
          "MaxHp": 27,
          "Block": 0,
          "IntentDamage": 7,
          "IntentType": "Attack",
          "VulnerableStacks": 0,
          "WeakStacks": 0,
          "StrengthStacks": 0,
          "Powers": [
            {
              "Name": "SkittishPower",
              "Amount": 6
            }
          ]
        },
        {
          "Index": 3,
          "Id": "PHANTASMAL_GARDENER",
          "Hp": 30,
          "MaxHp": 30,
          "Block": 0,
          "IntentDamage": 0,
          "IntentType": "Buff",
          "VulnerableStacks": 0,
          "WeakStacks": 0,
          "StrengthStacks": 0,
          "Powers": [
            {
              "Name": "SkittishPower",
              "Amount": 6
            }
          ]
        }
      ],
      "PlayerPowers": {
        "Strength": 0,
        "Dexterity": 0,
        "Weak": 0,
        "Frail": 0,
        "Vulnerable": 0
      },
      "Orbs": {
        "OrbSlots": 0,
        "Lightning": 0,
        "Frost": 0,
        "Dark": 0,
        "Plasma": 0,
        "Focus": 0,
        "Stars": 0
      },
      "PotionIds": [
        "STRENGTH_POTION"
      ],
      "PotionCount": 1,
      "SolverPlan": {
        "Actions": [
          "PLAY DEFEND_IRONCLAD -\u003E self",
          "USE_POTION STRENGTH_POTION",
          "PLAY PERFECTED_STRIKE -\u003E PHANTASMAL_GARDENER",
          "END_TURN"
        ],
        "EstimatedDamage": 32,
        "EstimatedBlock": 5,
        "Score": "Dmg=32 Blk=5 In=15 Cards=4 Score=979 States=1268 Char=IRONCLAD Src=reflection: dmg=14 blk=0",
        "StatesExplored": 1268
      },
      "ActionResults": [
        {
          "CardId": "DEFEND_IRONCLAD",
          "Success": true
        }
      ],
      "Outcome": {
        "HpAfter": 35,
        "BlockAfter": 5,
        "DamageTaken": 0,
        "EnemiesKilled": 0,
        "EnergyRemaining": 0,
        "PlayableCardsNotPlayed": 2,
        "TotalPlayableInHand": 5,
        "Issues": [
          "CARDS_UNPLAYED: 2 playable cards left at 0 energy"
        ]
      }
    },
    {
      "TurnNumber": 2,
      "Energy": 2,
      "Block": 5,
      "Hp": 35,
      "MaxHp": 80,
      "DrawPileCount": 15,
      "DiscardPileCount": 1,
      "Hand": [
        {
          "Id": "PERFECTED_STRIKE",
          "Cost": 2
        },
        {
          "Id": "STRIKE_IRONCLAD",
          "Cost": 1
        },
        {
          "Id": "STRIKE_IRONCLAD",
          "Cost": 1
        },
        {
          "Id": "UNRELENTING",
          "Cost": 2
        }
      ],
      "Enemies": [
        {
          "Index": 0,
          "Id": "PHANTASMAL_GARDENER",
          "Hp": 26,
          "MaxHp": 26,
          "Block": 0,
          "IntentDamage": 3,
          "IntentType": "Attack",
          "VulnerableStacks": 0,
          "WeakStacks": 0,
          "StrengthStacks": 0,
          "Powers": [
            {
              "Name": "SkittishPower",
              "Amount": 6
            }
          ]
        },
        {
          "Index": 1,
          "Id": "PHANTASMAL_GARDENER",
          "Hp": 29,
          "MaxHp": 29,
          "Block": 0,
          "IntentDamage": 5,
          "IntentType": "Attack",
          "VulnerableStacks": 0,
          "WeakStacks": 0,
          "StrengthStacks": 0,
          "Powers": [
            {
              "Name": "SkittishPower",
              "Amount": 6
            }
          ]
        },
        {
          "Index": 2,
          "Id": "PHANTASMAL_GARDENER",
          "Hp": 27,
          "MaxHp": 27,
          "Block": 0,
          "IntentDamage": 7,
          "IntentType": "Attack",
          "VulnerableStacks": 0,
          "WeakStacks": 0,
          "StrengthStacks": 0,
          "Powers": [
            {
              "Name": "SkittishPower",
              "Amount": 6
            }
          ]
        },
        {
          "Index": 3,
          "Id": "PHANTASMAL_GARDENER",
          "Hp": 30,
          "MaxHp": 30,
          "Block": 0,
          "IntentDamage": 0,
          "IntentType": "Buff",
          "VulnerableStacks": 0,
          "WeakStacks": 0,
          "StrengthStacks": 0,
          "Powers": [
            {
              "Name": "SkittishPower",
              "Amount": 6
            }
          ]
        }
      ],
      "PlayerPowers": {
        "Strength": 2,
        "Dexterity": 0,
        "Weak": 0,
        "Frail": 0,
        "Vulnerable": 0
      },
      "Orbs": {
        "OrbSlots": 0,
        "Lightning": 0,
        "Frost": 0,
        "Dark": 0,
        "Plasma": 0,
        "Focus": 0,
        "Stars": 0
      },
      "PotionIds": [],
      "PotionCount": 0,
      "SolverPlan": {
        "Actions": [
          "PLAY PERFECTED_STRIKE -\u003E PHANTASMAL_GARDENER",
          "END_TURN"
        ],
        "EstimatedDamage": 34,
        "EstimatedBlock": 0,
        "Score": "Dmg=34 Blk=0 In=15 Cards=2 Score=874 States=48 Char=IRONCLAD Src=reflection: dmg=16 blk=0",
        "StatesExplored": 48
      },
      "ActionResults": [
        {
          "CardId": "PERFECTED_STRIKE",
          "Success": true,
          "Target": "PHANTASMAL_GARDENER"
        }
      ],
      "Outcome": {
        "HpAfter": 25,
        "BlockAfter": 0,
        "DamageTaken": 10,
        "EnemiesKilled": 0,
        "EnergyRemaining": 1,
        "PlayableCardsNotPlayed": 3,
        "TotalPlayableInHand": 4,
        "Issues": [
          "ENERGY_WASTED: 1 energy left, 3/4 playable cards not used"
        ]
      }
    },
    {
      "TurnNumber": 3,
      "Energy": 3,
      "Block": 0,
      "Hp": 25,
      "MaxHp": 80,
      "DrawPileCount": 10,
      "DiscardPileCount": 5,
      "Hand": [
        {
          "Id": "DEFEND_IRONCLAD",
          "Cost": 1
        },
        {
          "Id": "HEMOKINESIS",
          "Cost": 1
        },
        {
          "Id": "DEFEND_IRONCLAD",
          "Cost": 1
        },
        {
          "Id": "WHIRLWIND",
          "Cost": -1
        },
        {
          "Id": "SECOND_WIND",
          "Cost": 1
        }
      ],
      "Enemies": [
        {
          "Index": 0,
          "Id": "PHANTASMAL_GARDENER",
          "Hp": 26,
          "MaxHp": 26,
          "Block": 0,
          "IntentDamage": 0,
          "IntentType": "Buff",
          "VulnerableStacks": 0,
          "WeakStacks": 0,
          "StrengthStacks": 0,
          "Powers": [
            {
              "Name": "SkittishPower",
              "Amount": 6
            }
          ]
        },
        {
          "Index": 1,
          "Id": "PHANTASMAL_GARDENER",
          "Hp": 29,
          "MaxHp": 29,
          "Block": 0,
          "IntentDamage": 7,
          "IntentType": "Attack",
          "VulnerableStacks": 0,
          "WeakStacks": 0,
          "StrengthStacks": 0,
          "Powers": [
            {
              "Name": "SkittishPower",
              "Amount": 6
            }
          ]
        },
        {
          "Index": 2,
          "Id": "PHANTASMAL_GARDENER",
          "Hp": 1,
          "MaxHp": 27,
          "Block": 0,
          "IntentDamage": 3,
          "IntentType": "Attack",
          "VulnerableStacks": 0,
          "WeakStacks": 0,
          "StrengthStacks": 0,
          "Powers": [
            {
              "Name": "SkittishPower",
              "Amount": 6
            }
          ]
        },
        {
          "Index": 3,
          "Id": "PHANTASMAL_GARDENER",
          "Hp": 30,
          "MaxHp": 30,
          "Block": 0,
          "IntentDamage": 7,
          "IntentType": "Attack",
          "VulnerableStacks": 0,
          "WeakStacks": 0,
          "StrengthStacks": 2,
          "Powers": [
            {
              "Name": "SkittishPower",
              "Amount": 6
            },
            {
              "Name": "StrengthPower",
              "Amount": 2
            }
          ]
        }
      ],
      "PlayerPowers": {
        "Strength": 2,
        "Dexterity": 0,
        "Weak": 0,
        "Frail": 0,
        "Vulnerable": 0
      },
      "Orbs": {
        "OrbSlots": 0,
        "Lightning": 0,
        "Frost": 0,
        "Dark": 0,
        "Plasma": 0,
        "Focus": 0,
        "Stars": 0
      },
      "PotionIds": [],
      "PotionCount": 0,
      "SolverPlan": {
        "Actions": [
          "PLAY WHIRLWIND -\u003E PHANTASMAL_GARDENER",
          "PLAY HEMOKINESIS -\u003E PHANTASMAL_GARDENER",
          "END_TURN"
        ],
        "EstimatedDamage": 68,
        "EstimatedBlock": 0,
        "Score": "Dmg=68 Blk=0 In=17 Cards=3 Score=913 States=303 Char=IRONCLAD Src=reflection: dmg=0 blk=5",
        "StatesExplored": 303
      },
      "ActionResults": [
        {
          "CardId": "WHIRLWIND",
          "Success": true,
          "Target": "PHANTASMAL_GARDENER"
        },
        {
          "CardId": "HEMOKINESIS",
          "Success": false,
          "FailReason": "not playable: EnergyCostTooHigh",
          "Target": "PHANTASMAL_GARDENER"
        }
      ],
      "Outcome": {
        "HpAfter": 11,
        "BlockAfter": 0,
        "DamageTaken": 14,
        "EnemiesKilled": 1,
        "EnergyRemaining": 0,
        "PlayableCardsNotPlayed": 3,
        "TotalPlayableInHand": 5,
        "Issues": [
          "CARDS_UNPLAYED: 3 playable cards left at 0 energy"
        ]
      }
    },
    {
      "TurnNumber": 4,
      "Energy": 3,
      "Block": 0,
      "Hp": 11,
      "MaxHp": 80,
      "DrawPileCount": 5,
      "DiscardPileCount": 10,
      "Hand": [
        {
          "Id": "DEFEND_IRONCLAD",
          "Cost": 1
        },
        {
          "Id": "STRIKE_IRONCLAD",
          "Cost": 1
        },
        {
          "Id": "STRIKE_IRONCLAD",
          "Cost": 1
        },
        {
          "Id": "HEADBUTT",
          "Cost": 1
        },
        {
          "Id": "THE_BOMB",
          "Cost": 2
        }
      ],
      "Enemies": [
        {
          "Index": 0,
          "Id": "PHANTASMAL_GARDENER",
          "Hp": 5,
          "MaxHp": 26,
          "Block": 0,
          "IntentDamage": 7,
          "IntentType": "Attack",
          "VulnerableStacks": 0,
          "WeakStacks": 0,
          "StrengthStacks": 2,
          "Powers": [
            {
              "Name": "SkittishPower",
              "Amount": 6
            },
            {
              "Name": "StrengthPower",
              "Amount": 2
            }
          ]
        },
        {
          "Index": 1,
          "Id": "PHANTASMAL_GARDENER",
          "Hp": 8,
          "MaxHp": 29,
          "Block": 0,
          "IntentDamage": 3,
          "IntentType": "Attack",
          "VulnerableStacks": 0,
          "WeakStacks": 0,
          "StrengthStacks": 0,
          "Powers": [
            {
              "Name": "SkittishPower",
              "Amount": 6
            }
          ]
        },
        {
          "Index": 2,
          "Id": "PHANTASMAL_GARDENER",
          "Hp": 9,
          "MaxHp": 30,
          "Block": 0,
          "IntentDamage": 9,
          "IntentType": "Attack",
          "VulnerableStacks": 0,
          "WeakStacks": 0,
          "StrengthStacks": 2,
          "Powers": [
            {
              "Name": "SkittishPower",
              "Amount": 6
            },
            {
              "Name": "StrengthPower",
              "Amount": 2
            }
          ]
        }
      ],
      "PlayerPowers": {
        "Strength": 2,
        "Dexterity": 0,
        "Weak": 0,
        "Frail": 0,
        "Vulnerable": 0
      },
      "Orbs": {
        "OrbSlots": 0,
        "Lightning": 0,
        "Frost": 0,
        "Dark": 0,
        "Plasma": 0,
        "Focus": 0,
        "Stars": 0
      },
      "PotionIds": [],
      "PotionCount": 0,
      "SolverPlan": {
        "Actions": [
          "PLAY HEADBUTT -\u003E PHANTASMAL_GARDENER",
          "PLAY STRIKE_IRONCLAD -\u003E PHANTASMAL_GARDENER",
          "PLAY STRIKE_IRONCLAD -\u003E PHANTASMAL_GARDENER",
          "END_TURN"
        ],
        "EstimatedDamage": 33,
        "EstimatedBlock": 0,
        "Score": "Dmg=33 Blk=0 In=19 Cards=4 Score=1575 States=229 Char=IRONCLAD Src=reflection: dmg=11 blk=0",
        "StatesExplored": 229
      },
      "ActionResults": [
        {
          "CardId": "HEADBUTT",
          "Success": true,
          "Target": "PHANTASMAL_GARDENER"
        }
      ],
      "Outcome": {
        "HpAfter": 11,
        "BlockAfter": 0,
        "DamageTaken": 0,
        "EnemiesKilled": 1,
        "EnergyRemaining": 0,
        "PlayableCardsNotPlayed": 2,
        "TotalPlayableInHand": 5,
        "Issues": [
          "CARDS_UNPLAYED: 2 playable cards left at 0 energy"
        ]
      }
    },
    {
      "TurnNumber": 5,
      "Energy": 3,
      "Block": 0,
      "Hp": 11,
      "MaxHp": 80,
      "DrawPileCount": 6,
      "DiscardPileCount": 10,
      "Hand": [
        {
          "Id": "DEFEND_IRONCLAD",
          "Cost": 1
        },
        {
          "Id": "STRIKE_IRONCLAD",
          "Cost": 1
        },
        {
          "Id": "STRIKE_IRONCLAD",
          "Cost": 1
        },
        {
          "Id": "THE_BOMB",
          "Cost": 2
        }
      ],
      "Enemies": [
        {
          "Index": 0,
          "Id": "PHANTASMAL_GARDENER",
          "Hp": 8,
          "MaxHp": 29,
          "Block": 0,
          "IntentDamage": 3,
          "IntentType": "Attack",
          "VulnerableStacks": 0,
          "WeakStacks": 0,
          "StrengthStacks": 0,
          "Powers": [
            {
              "Name": "SkittishPower",
              "Amount": 6
            }
          ]
        },
        {
          "Index": 1,
          "Id": "PHANTASMAL_GARDENER",
          "Hp": 9,
          "MaxHp": 30,
          "Block": 0,
          "IntentDamage": 9,
          "IntentType": "Attack",
          "VulnerableStacks": 0,
          "WeakStacks": 0,
          "StrengthStacks": 2,
          "Powers": [
            {
              "Name": "SkittishPower",
              "Amount": 6
            },
            {
              "Name": "StrengthPower",
              "Amount": 2
            }
          ]
        }
      ],
      "PlayerPowers": {
        "Strength": 2,
        "Dexterity": 0,
        "Weak": 0,
        "Frail": 0,
        "Vulnerable": 0
      },
      "Orbs": {
        "OrbSlots": 0,
        "Lightning": 0,
        "Frost": 0,
        "Dark": 0,
        "Plasma": 0,
        "Focus": 0,
        "Stars": 0
      },
      "PotionIds": [],
      "PotionCount": 0,
      "SolverPlan": {
        "Actions": [
          "PLAY DEFEND_IRONCLAD -\u003E self",
          "PLAY STRIKE_IRONCLAD -\u003E PHANTASMAL_GARDENER",
          "PLAY STRIKE_IRONCLAD -\u003E PHANTASMAL_GARDENER",
          "END_TURN"
        ],
        "EstimatedDamage": 20,
        "EstimatedBlock": 8,
        "Score": "Dmg=20 Blk=8 In=12 Cards=4 Score=-196 States=36 Char=IRONCLAD Src=reflection: dmg=8 blk=0",
        "StatesExplored": 36
      },
      "ActionResults": [
        {
          "CardId": "DEFEND_IRONCLAD",
          "Success": true
        },
        {
          "CardId": "STRIKE_IRONCLAD",
          "Success": true,
          "Target": "PHANTASMAL_GARDENER"
        },
        {
          "CardId": "STRIKE_IRONCLAD",
          "Success": true,
          "Target": "PHANTASMAL_GARDENER"
        }
      ],
      "Outcome": {
        "HpAfter": 10,
        "BlockAfter": 0,
        "DamageTaken": 1,
        "EnemiesKilled": 1,
        "EnergyRemaining": 0,
        "PlayableCardsNotPlayed": 1,
        "TotalPlayableInHand": 4,
        "Issues": [
          "CARDS_UNPLAYED: 1 playable cards left at 0 energy"
        ]
      }
    },
    {
      "TurnNumber": 6,
      "Energy": 3,
      "Block": 0,
      "Hp": 10,
      "MaxHp": 80,
      "DrawPileCount": 1,
      "DiscardPileCount": 14,
      "Hand": [
        {
          "Id": "PERFECTED_STRIKE",
          "Cost": 2
        },
        {
          "Id": "STRIKE_IRONCLAD",
          "Cost": 1
        },
        {
          "Id": "HEADBUTT",
          "Cost": 1
        },
        {
          "Id": "MOLTEN_FIST",
          "Cost": 1
        },
        {
          "Id": "GREED",
          "Cost": -1
        }
      ],
      "Enemies": [
        {
          "Index": 0,
          "Id": "PHANTASMAL_GARDENER",
          "Hp": 1,
          "MaxHp": 30,
          "Block": 0,
          "IntentDamage": 9,
          "IntentType": "Attack",
          "VulnerableStacks": 0,
          "WeakStacks": 0,
          "StrengthStacks": 2,
          "Powers": [
            {
              "Name": "SkittishPower",
              "Amount": 6
            },
            {
              "Name": "StrengthPower",
              "Amount": 2
            }
          ]
        }
      ],
      "PlayerPowers": {
        "Strength": 2,
        "Dexterity": 0,
        "Weak": 0,
        "Frail": 0,
        "Vulnerable": 0
      },
      "Orbs": {
        "OrbSlots": 0,
        "Lightning": 0,
        "Frost": 0,
        "Dark": 0,
        "Plasma": 0,
        "Focus": 0,
        "Stars": 0
      },
      "PotionIds": [],
      "PotionCount": 0,
      "SolverPlan": {
        "Actions": [
          "PLAY PERFECTED_STRIKE -\u003E PHANTASMAL_GARDENER",
          "END_TURN"
        ],
        "EstimatedDamage": 28,
        "EstimatedBlock": 0,
        "Score": "Dmg=28 Blk=0 In=9 Cards=2 Score=-1741 States=4 Char=IRONCLAD Src=reflection: dmg=12 blk=0",
        "StatesExplored": 4
      },
      "ActionResults": [
        {
          "CardId": "PERFECTED_STRIKE",
          "Success": true,
          "Target": "PHANTASMAL_GARDENER"
        }
      ],
      "Outcome": {
        "HpAfter": 16,
        "BlockAfter": 0,
        "DamageTaken": 0,
        "EnemiesKilled": 0,
        "EnergyRemaining": 0,
        "PlayableCardsNotPlayed": 0,
        "TotalPlayableInHand": 0,
        "Issues": []
      }
    }
  ]
}